{
    "_links": {
        "self": {
            "href": "http:\/\/proyectofinal.ddev.local\/sites\/default\/files\/2019-05\/generateImage_ialcZq.jpg"
        },
        "type": {
            "href": "http:\/\/drupal.org\/rest\/type\/file\/file"
        },
        "http:\/\/drupal.org\/rest\/relation\/file\/file\/uid": [
            {
                "href": "http:\/\/proyectofinal.ddev.local\/user\/1?_format=hal_json"
            }
        ]
    },
    "fid": [
        {
            "value": 10
        }
    ],
    "uuid": [
        {
            "value": "0e9f20b1-0bc9-44b3-af51-51855dcd2b1f"
        }
    ],
    "langcode": [
        {
            "value": "en"
        }
    ],
    "_embedded": {
        "http:\/\/drupal.org\/rest\/relation\/file\/file\/uid": [
            {
                "_links": {
                    "self": {
                        "href": "http:\/\/proyectofinal.ddev.local\/user\/1?_format=hal_json"
                    },
                    "type": {
                        "href": "http:\/\/drupal.org\/rest\/type\/user\/user"
                    }
                },
                "uuid": [
                    {
                        "value": "72e0397b-8e0d-4ea2-b088-a51a5b56f416"
                    }
                ]
            }
        ]
    },
    "filename": [
        {
            "value": "generateImage_ialcZq.jpg"
        }
    ],
    "uri": [
        {
            "value": "public:\/\/2019-05\/generateImage_ialcZq.jpg",
            "url": "\/sites\/default\/files\/2019-05\/generateImage_ialcZq.jpg"
        }
    ],
    "filemime": [
        {
            "value": "image\/jpeg"
        }
    ],
    "filesize": [
        {
            "value": 5708
        }
    ],
    "status": [
        {
            "value": true
        }
    ],
    "created": [
        {
            "value": "2019-05-15T16:12:27+00:00",
            "format": "Y-m-d\\TH:i:sP"
        }
    ],
    "changed": [
        {
            "value": "2019-05-15T16:12:27+00:00",
            "format": "Y-m-d\\TH:i:sP"
        }
    ]
}